pysnooper/__init__.py
pysnooper/pycompat.py
pysnooper/tracer.py
pysnooper/utils.py
pysnooper/variables.py
PySnooper-1.2.2.dist-info/AUTHORS
PySnooper-1.2.2.dist-info/LICENSE
PySnooper-1.2.2.dist-info/METADATA
PySnooper-1.2.2.dist-info/WHEEL
PySnooper-1.2.2.dist-info/top_level.txt
PySnooper-1.2.2.dist-info/RECORD
