Metadata-Version: 2.1
Name: PySnooper
Version: 1.2.2
Summary: A poor man's debugger for Python.
Home-page: https://github.com/cool-RR/PySnooper
Author: Ram Rachum
Author-email: ram@rachum.com
Classifier: Environment :: Console
Classifier: Intended Audience :: Developers
Classifier: Programming Language :: Python :: 2.7
Classifier: Programming Language :: Python :: 3.4
Classifier: Programming Language :: Python :: 3.5
Classifier: Programming Language :: Python :: 3.6
Classifier: Programming Language :: Python :: 3.7
Classifier: Programming Language :: Python :: 3.8
Classifier: Programming Language :: Python :: 3.9
Classifier: Programming Language :: Python :: 3.10
Classifier: Programming Language :: Python :: 3.11
Classifier: Programming Language :: Python :: Implementation :: CPython
Classifier: Programming Language :: Python :: Implementation :: PyPy
Classifier: License :: OSI Approved :: MIT License
Classifier: Operating System :: OS Independent
Classifier: Topic :: Software Development :: Debuggers
License-File: LICENSE
License-File: AUTHORS
Provides-Extra: tests
Requires-Dist: pytest; extra == "tests"
